snraspi/__init__.py
snraspi/sensors/EnvironmentSensor.py
snraspi/sensors/__init__.py
snraspi_lib-1.0.6.dist-info/LICENSE
snraspi_lib-1.0.6.dist-info/METADATA
snraspi_lib-1.0.6.dist-info/WHEEL
snraspi_lib-1.0.6.dist-info/top_level.txt
snraspi_lib-1.0.6.dist-info/RECORD
